{
  "links": [
    {
      "icon": "far fa-laugh-beam",
      "title": "Persoonlijk blog",
      "description": "Op mijn blog post ik over het leven als startende tech docent. Daarnaast plaats ik ook geregeld eigen 'tutorials' over zelf gemaakte projecten.",
      "link": "https://ldegoeij.nl",
      "categories": [
        "home"
      ],
      "tags": []
    },
    {
      "icon": "fas fa-book-open",
      "title": "Basisopleiding didactiek",
      "description": "Op mijn blog bevind zich een subsite over mijn opdrachten betreft de basisopleiding didactiek.",
      "link": "https://ldegoeij.nl/bdb",
      "categories": [
        "home"
      ],
      "tags": []
    },
    {
      "icon": "fab fa-github",
      "title": "CMGT GitHub account",
      "description": "Op het GitHub account van CMGT kun je lesmateriaal en verschillende projecten vinden binnen de opleiding.",
      "link": "https://github.com/HR-CMGT",
      "categories": [
        "modules"
      ],
      "tags": [
        "Programmeren"
      ]
    }
  ]
}